pyfax/__init__.py
pyfax/_config.py
pyfax/page.py
pyfax/version.py
pyfax/pages/__init__.py
pyfax/pages/test_page.py
pyfax/tools/__init__.py
pyfax/tools/url_helpers.py
pyfax-2024.2.8.dist-info/LICENSE
pyfax-2024.2.8.dist-info/WHEEL
pyfax-2024.2.8.dist-info/METADATA
pyfax-2024.2.8.dist-info/RECORD
