Metadata-Version: 2.1
Name: pyfax
Version: 2024.2.8
Summary: a Python library for generating teletext tti files
Author-email: Matthew Scroggs <pyfax@mscroggs.co.uk>
Requires-Python: >=3.8.0
Requires-Dist: requests
Requires-Dist: feedparser
Requires-Dist: sphinx ; extra == "docs"
Requires-Dist: sphinx-autoapi ; extra == "docs"
Requires-Dist: ruff ; extra == "style"
Requires-Dist: flake8 ; extra == "style"
Requires-Dist: mypy ; extra == "style"
Requires-Dist: isort ; extra == "style"
Requires-Dist: pytest ; extra == "test"
Project-URL: documentation, https://pyfax.readthedocs.io/en/latest/
Project-URL: homepage, https://github.com/mscroggs/pyfax
Project-URL: repository, https://github.com/mscroggs/pyfax
Provides-Extra: docs
Provides-Extra: style
Provides-Extra: test
